admin_honeypot/__init__.py
admin_honeypot/admin.py
admin_honeypot/forms.py
admin_honeypot/listeners.py
admin_honeypot/models.py
admin_honeypot/signals.py
admin_honeypot/urls.py
admin_honeypot/views.py
admin_honeypot/migrations/0001_initial.py
admin_honeypot/migrations/0002_auto_20160208_0854.py
admin_honeypot/migrations/__init__.py
admin_honeypot/templates/admin_honeypot/email_message.txt
admin_honeypot/templates/admin_honeypot/email_subject.txt
admin_honeypot/templates/admin_honeypot/login.html
django_admin_honeypot_1.2.0-1.2.0.dist-info/LICENSE
django_admin_honeypot_1.2.0-1.2.0.dist-info/METADATA
django_admin_honeypot_1.2.0-1.2.0.dist-info/WHEEL
django_admin_honeypot_1.2.0-1.2.0.dist-info/top_level.txt
django_admin_honeypot_1.2.0-1.2.0.dist-info/RECORD
